<tvshow>
    <title>11eyes</title>
    <originaltitle>11eyes</originaltitle>
    <sorttitle>いれぶんあいず</sorttitle>
    <set>11eyes -罪と罰と贖いの少女-</set>
    <mpaa>TV-14</mpaa>
    <plot>平凡な生活を送っていた皐月駆だが、ある日幼なじみの水奈瀬ゆかと共に、突然不気味な異世界へ迷い込んでしまうことに…。

血の色にも似た不気味に赤く染まる空に、漆黒の巨大な月。そんな『赤い夜』の世界に、呆気にとられる駆とゆか…。

さらに、二人の周りに異形の怪物が現れ、襲いかかる。</plot>
    <tagline>11eyes</tagline>
    <rating>4.2</rating>
    <premiered>2009-10-06</premiered>
    <studio>動画工房</studio>
    <genre>憂鬱</genre>
    <genre>ハーレム</genre>
    <genre>エロい</genre>
    <genre>現代ファンタジー</genre>
    <genre>アクション</genre>
    <actor>
        <name>小野大輔</name>
        <role>皐月駆</role>
        <thumb>https://example.com/cast/小野大輔.jpg</thumb>
    </actor>
    <actor>
        <name>後藤麻衣</name>
        <role>水奈瀬ゆか</role>
        <thumb>https://example.com/cast/後藤麻衣.jpg</thumb>
    </actor>
</tvshow>
